{
  "name": "DynamicProductsOutput",
  "fields": [
    {
      "fieldName": "fieldName",
      "fieldType": "String"
    },
    {
      "fieldName": "fieldSource",
      "fieldType": "String"
    },
    {
      "fieldName": "fieldExpression",
      "fieldType": "String"
    }
  ],
  "relationships": [],
  "changelogDate": "20201209011120",
  "entityTableName": "dynamic_products_output",
  "dto": "no",
  "pagination": "no",
  "service": "no",
  "jpaMetamodelFiltering": false,
  "fluentMethods": true,
  "readOnly": false,
  "embedded": false,
  "clientRootFolder": "productCatalog",
  "applications": "*",
  "microserviceName": "productCatalog"
}
